cymr/__init__.py
cymr/cmr.py
cymr/cmr_lba.py
cymr/fit.py
cymr/lba.cpython-38-darwin.so
cymr/network.py
cymr/operations.cpython-38-darwin.so
cymr/parameters.py
cymr/data/Morton2013_mixed.csv
cymr-0.10.1.dist-info/LICENSE
cymr-0.10.1.dist-info/METADATA
cymr-0.10.1.dist-info/WHEEL
cymr-0.10.1.dist-info/top_level.txt
cymr-0.10.1.dist-info/RECORD
