Metadata-Version: 2.1
Name: cymr
Version: 0.10.1
Summary: CMR implemented using Cython.
Home-page: http://github.com/mortonne/cymr
Author: Neal Morton
Author-email: mortonne@gmail.com
License: GPLv3
Platform: UNKNOWN
Classifier: License :: OSI Approved :: GNU General Public License v3 (GPLv3)
Classifier: Programming Language :: Python :: 3.8
Provides-Extra: docs
Requires-Dist: sphinx ; extra == 'docs'
Requires-Dist: pydata-sphinx-theme ; extra == 'docs'
Requires-Dist: ipython ; extra == 'docs'
Provides-Extra: test
Requires-Dist: pytest ; extra == 'test'
Requires-Dist: codecov ; extra == 'test'
Requires-Dist: pytest-cov ; extra == 'test'
